setup.py
jdcloud_sdk/__init__.py
jdcloud_sdk/core/__init__.py
jdcloud_sdk/core/config.py
jdcloud_sdk/core/const.py
jdcloud_sdk/core/credential.py
jdcloud_sdk/core/exception.py
jdcloud_sdk/core/jdcloudclient.py
jdcloud_sdk/core/jdcloudrequest.py
jdcloud_sdk/core/jdcloudresponse.py
jdcloud_sdk/core/logger.py
jdcloud_sdk/core/parameterbuilder.py
jdcloud_sdk/core/signer.py
jdcloud_sdk/core/util.py
jdcloud_sdk/core/version.py
jdcloud_sdk_core.egg-info/PKG-INFO
jdcloud_sdk_core.egg-info/SOURCES.txt
jdcloud_sdk_core.egg-info/dependency_links.txt
jdcloud_sdk_core.egg-info/requires.txt
jdcloud_sdk_core.egg-info/top_level.txt