Metadata-Version: 1.0
Name: jdcloud-sdk-core
Version: 1.3.1
Summary: JDCloud SDK Core for Python
Home-page: UNKNOWN
Author: JDCloud API Gateway Team
Author-email: UNKNOWN
License: Apache License V2.0
Platform: UNKNOWN
